messthaler_wulff/__init__.py
messthaler_wulff/__main__.py
messthaler_wulff/additive_simulation.py
messthaler_wulff/common_objects.py
messthaler_wulff/data.py
messthaler_wulff/decorators.py
messthaler_wulff/explorative_simulation.py
messthaler_wulff/minimiser_simulation.py
messthaler_wulff/mode_explore.py
messthaler_wulff/mode_interactive.py
messthaler_wulff/mode_minimisers.py
messthaler_wulff/mode_simulate.py
messthaler_wulff/mode_view.py
messthaler_wulff/objects.py
messthaler_wulff/progress.py
messthaler_wulff/simulation_state.py
messthaler_wulff/terminal_formatting.py
messthaler_wulff/utils.py
messthaler_wulff/version.py
messthaler_wulff-2025.12.14.dist-info/METADATA
messthaler_wulff-2025.12.14.dist-info/WHEEL
messthaler_wulff-2025.12.14.dist-info/entry_points.txt
messthaler_wulff-2025.12.14.dist-info/licenses/LICENSE.txt
messthaler_wulff-2025.12.14.dist-info/RECORD
