Metadata-Version: 2.4
Name: messthaler-wulff
Version: 2025.12.14
Author-email: Guenthner <guenthner.jonathan@gmail.com>
License-File: LICENSE.txt
Keywords: Wulff,Wulff Crystals
Classifier: License :: OSI Approved :: MIT License
Classifier: Operating System :: OS Independent
Classifier: Programming Language :: Python :: 3
Requires-Python: >=3.8
Requires-Dist: matplotlib
Requires-Dist: open3d
Requires-Dist: prettytable
Requires-Dist: psutil
Requires-Dist: scipy
Requires-Dist: sortedcontainers
